CHANGELOG.md
LICENSE.md
MANIFEST.in
README.md
setup.py
iparapheur_utils.beta.egg-info/PKG-INFO
iparapheur_utils.beta.egg-info/SOURCES.txt
iparapheur_utils.beta.egg-info/dependency_links.txt
iparapheur_utils.beta.egg-info/entry_points.txt
iparapheur_utils.beta.egg-info/requires.txt
iparapheur_utils.beta.egg-info/top_level.txt
parapheur/__init__.py
parapheur/core.py
parapheur/script.cfg
parapheur/configs/export.cfg
parapheur/configs/import.cfg
parapheur/configs/ldapsearch.cfg
parapheur/configs/patch.cfg
parapheur/configs/pushdoc.cfg
parapheur/configs/recuparchives.cfg
parapheur/configs/recupfull.cfg
parapheur/configs/reset_admin_password.cfg
parapheur/configs/script.cfg
parapheur/configs/template.cfg
parapheur/files/private.pem
parapheur/files/public.pem
parapheur/files/crontab/450.txt
parapheur/files/crontab/460.txt
parapheur/files/crontab/468.txt
parapheur/files/crontab/470.txt
parapheur/files/templates/parapheur-admin-suppression.ftl
parapheur/files/templates/parapheur-admin-transfert.ftl
parapheur/files/templates/parapheur-current-reception.ftl
parapheur/files/templates/parapheur-current-retard.ftl
parapheur/files/templates/parapheur-current-tdt-ok-archivage.ftl
parapheur/files/templates/parapheur-diffusion-archive.ftl
parapheur/files/templates/parapheur-diffusion-emission.ftl
parapheur/files/templates/parapheur-diffusion-retour.ftl
parapheur/files/templates/parapheur-diffusion-tdt-ok.ftl
parapheur/files/templates/parapheur-diffusion-visa.ftl
parapheur/files/templates/parapheur-digest-mail.ftl
parapheur/files/templates/parapheur-dossier-email.ftl
parapheur/files/templates/parapheur-mail-approve.ftl
parapheur/files/templates/parapheur-mail-archive.ftl
parapheur/files/templates/parapheur-mail-delegation.ftl
parapheur/files/templates/parapheur-mail-deleteAdmin.ftl
parapheur/files/templates/parapheur-mail-moveAdmin.ftl
parapheur/files/templates/parapheur-mail-print.ftl
parapheur/files/templates/parapheur-mail-reject.ftl
parapheur/files/templates/parapheur-mail-remord.ftl
parapheur/files/templates/parapheur-mail-resetpassword.ftl
parapheur/files/templates/parapheur-mail-retard.ftl
parapheur/files/templates/parapheur-mail-reviewing.ftl
parapheur/files/templates/parapheur-mail-tiers.ftl
