Metadata-Version: 2.1
Name: iparapheur-utils.beta
Version: 0.0.1.post456051
Summary: Client python pour i-Parapheur
Home-page: https://gitlab.libriciel.fr/i-parapheur/client-python
Author: Libriciel SCOP
Author-email: contact@libriciel.fr
License: AGPLv3
Platform: UNKNOWN
